jsspp/__init__.py
jsspp/osp/__init__.py
jsspp/osp/cli.py
jsspp/osp/model/__init__.py
jsspp/osp/model/environment/__init__.py
jsspp/osp/model/environment/mapper.py
jsspp/osp/model/environment/events/__init__.py
jsspp/osp/model/environment/resources/__init__.py
jsspp/osp/model/environment/resources/machine.py
jsspp/osp/parser/__init__.py
jsspp/osp/parser/environment.py
jsspp/osp/parser/workload.py
jsspp/osp/util/__init__.py
jsspp/osp/util/jsonref.py
jsspp/osp/validation/__init__.py
jsspp/osp/validation/schema.py
jsspp_osp-1.0.0.dist-info/LICENSE.txt
jsspp_osp-1.0.0.dist-info/METADATA
jsspp_osp-1.0.0.dist-info/WHEEL
jsspp_osp-1.0.0.dist-info/entry_points.txt
jsspp_osp-1.0.0.dist-info/top_level.txt
jsspp_osp-1.0.0.dist-info/RECORD
