Metadata-Version: 2.1
Name: jsspp-osp
Version: 1.0.0
Summary: Tooling and documentation of of the formats used for Open Scheduling Problems (OSPs) of JSSPP
Home-page: https://github.com/atlarge-research/jsspp-osp
Author: @Large Research
Author-email: info@atlarge-research.com
License: MIT
Platform: UNKNOWN
Requires-Dist: jsonschema (==3.0.0a3)
